strcuta/__init__.py
strcuta/cursor.py
strcuta/frq.py
strcuta/otoini.py
strcuta/prefixmap.py
strcuta/voicebank.py
strcuta/wav.py
strcuta-0.0.17.dist-info/LICENSE_1_0.txt
strcuta-0.0.17.dist-info/METADATA
strcuta-0.0.17.dist-info/WHEEL
strcuta-0.0.17.dist-info/top_level.txt
strcuta-0.0.17.dist-info/RECORD
