Metadata-Version: 2.1
Name: strcuta
Version: 0.0.17
Summary: Loading UTAU voice banks into the Python data structure.
Home-page: https://github.com/takagiy/strcuta-py
Author: takagiy
Author-email: takagiy.4dev@gmail.com
License: UNKNOWN
Project-URL: Repository, https://github.com/takagiy/strcuta-py
Project-URL: Bug reports, https://github.com/takagiy/strcuta-py/issues
Platform: UNKNOWN
Classifier: License :: OSI Approved :: Boost Software License 1.0 (BSL-1.0)
Classifier: Development Status :: 3 - Alpha
Provides-Extra: play
Requires-Dist: sounddevice ; extra == 'play'
